{
  "items": [
    {
      "text": "Microgrants",
      "link": "#",
      "children": [
        {
          "text": "Apply",
          "link": "/grants/apply/"
        },
        {
          "text": "Grants",
          "link": "/grants/grants/"
        }
      ]
    },
    {
      "text": "Research",
      "link": "#",
      "children": [
        {
          "text": "Mitiq",
          "link": "/research/mitiq/"
        },
        {
          "text": "Metriq",
          "link": "/research/metriq/"
        },
        {
          "text": "Publications",
          "link": "/research/publications/"
        }
      ]
    },
    {
      "text": "Community",
      "link": "/community/"
    },
    {
      "text": "Blog",
      "link": "/blog/"
    },
    {
      "text": "Donate",
      "link": "/donate/"
    }
  ]
}
